LICENSE
MANIFEST.in
README.md
setup.py
libpythonpro/__init__.py
libpythonpro/github_api.py
libpythonpro/spam/__init__.py
libpythonpro/spam/db.py
libpythonpro/spam/enviador_de_email.py
libpythonpro/spam/main.py
libpythonpro/spam/modelos.py
libpythonpro/tests/__init__.py
libpythonpro/tests/test_exemplo.py
libpythonpro/tests/test_spam/__init__.py
libpythonpro/tests/test_spam/conftest.py
libpythonpro/tests/test_spam/test_enviador_de_email.py
libpythonpro/tests/test_spam/test_envio_para_base_de_usuarios.py
libpythonpro/tests/test_spam/test_usuarios.py
libpythonpro_gc.egg-info/PKG-INFO
libpythonpro_gc.egg-info/SOURCES.txt
libpythonpro_gc.egg-info/dependency_links.txt
libpythonpro_gc.egg-info/not-zip-safe
libpythonpro_gc.egg-info/requires.txt
libpythonpro_gc.egg-info/top_level.txt