Metadata-Version: 2.1
Name: libpythonpro-gc
Version: 0.2
Summary: Exercício de aprendizagem referente criação de projetos na linguagem Python, Curso Python Pro.
Home-page: https://github.com/GetulioCastro/pytools_pythonpro
Author: Getulio Castro
Author-email: augustoge71@gmail.com
License: GNU AFFERO GENERAL PUBLIC LICENSE
Platform: UNKNOWN
Classifier: Development Status :: 2 - Pre-Alpha
Classifier: Environment :: Console
Classifier: Intended Audience :: Developers
Classifier: License :: OSI Approved :: GNU Affero General Public License v3 or later (AGPLv3+)
Classifier: Operating System :: OS Independent
Classifier: Programming Language :: Python
Classifier: Programming Language :: Python :: 3.8
Classifier: Framework :: Pytest
